MANIFEST.in
README.md
setup.cfg
setup.py
ipython_pip_magics/__init__.py
ipython_pip_magics.egg-info/PKG-INFO
ipython_pip_magics.egg-info/SOURCES.txt
ipython_pip_magics.egg-info/dependency_links.txt
ipython_pip_magics.egg-info/top_level.txt