Metadata-Version: 1.1
Name: ipython-pip-magics
Version: 1.0.1
Summary: %pip magics for IPython
Home-page: https://github.com/stephanh42/ipython_pip_magics
Author: Stephan Houben
Author-email: stephanh42@gmail.com
License: MIT
Keywords: ipython pip
Platform: UNKNOWN
Classifier: Development Status :: 3 - Alpha
Classifier: Intended Audience :: Developers
Classifier: Topic :: Software Development :: Build Tools
Classifier: License :: OSI Approved :: MIT License
Classifier: Programming Language :: Python :: 3
Classifier: Programming Language :: Python :: 3.3
Classifier: Programming Language :: Python :: 3.4
